LICENSE
MANIFEST.in
README.md
requirements.txt
setup.py
jmsdb/__init__.py
jmsdb/assets.py
jmsdb/audits.py
jmsdb/auth.py
jmsdb/config.py
jmsdb/exception.py
jmsdb/models.py
jmsdb/orgs.py
jmsdb/perms.py
jmsdb/request.py
jmsdb/service.py
jmsdb/terminal.py
jmsdb/test_auth.py
jmsdb/test_perms.py
jmsdb/test_request.py
jmsdb/test_terminate.py
jmsdb/url.py
jmsdb/users.py
jmsdb/utils.py
jumpserver_omnidb_sdk.egg-info/PKG-INFO
jumpserver_omnidb_sdk.egg-info/SOURCES.txt
jumpserver_omnidb_sdk.egg-info/dependency_links.txt
jumpserver_omnidb_sdk.egg-info/requires.txt
jumpserver_omnidb_sdk.egg-info/top_level.txt
test/test_app_service.py
test/test_user_service.py