Metadata-Version: 2.1
Name: jumpserver-omnidb-sdk
Version: 0.0.8
Summary: Jumpserver python sdk tools
Home-page: http://jumpserver.org
Author: bingws
Author-email: 2423355719@qq.com
License: UNKNOWN
Keywords: jms jumpserver
Platform: UNKNOWN
Classifier: Development Status :: 5 - Production/Stable
Classifier: Intended Audience :: Developers
Classifier: License :: OSI Approved :: MIT License
Classifier: Operating System :: OS Independent
Classifier: Programming Language :: Python
Classifier: Programming Language :: Python :: 3.5
Classifier: Programming Language :: Python :: 3.6
